Metadata-Version: 2.1
Name: omletApi
Version: 1.1
Summary: using omAPI
Author-email: thekip077@gmail.com
